{
    "patches": [
        {
            "label": "2026-04-07_10-44-46",
            "content": "@@ -6,16 +6,17 @@\n ge main%0A\n+%0A\n import %22\n@@ -20,16 +20,17 @@\n t %22fmt%22%0A\n+%0A\n func mai\n@@ -39,137 +39,467 @@\n ) %7B%0A\n-    var totalAlbum, totalPossui int%0A%0A    contagem := make(map%5Bint%5Dint)%0A%0A    for i := 0; i %3C totalPossui; i++ %7B%0A        var num int\n+%09var qini, qdeix int%0A%09fmt.Scan(&qini)%0A%09pessoas := make(%5B%5Dint, qini)%0A%0A%09for i := 0; i %3C qini; i++ %7B%0A%09%09fmt.Scan(&pessoas%5Bi%5D)%0A%0A%09%7D%0A%09fmt.Scan(&qdeix)%0A%09sairam := make(%5B%5Dint, qdeix)%0A%09for i := 0; i %3C qdeix; i++ %7B%0A%09%09fmt.Scan(&sairam%5Bi%5D)%0A%09%7D%0A%0A%09for i := 0; i %3C qdeix; i++ %7B%0A%09%09for j := 0; j %3C qini; j++ %7B%0A%09%09%09if pessoas%5Bj%5D == sairam%5Bi%5D %7B%0A%09%09%09%09pessoas%5Bj%5D = 0%0A%09%09%09%7D%0A%09%09%7D%0A%09%7D%0A%09for i := 0; i %3C qini; i++ %7B%0A%09%09if pessoas%5Bi%5D != 0 %7B%0A%09%09%09fmt.Print(pessoas%5Bi%5D, %22 %22)%0A%09%09%7D%0A%09%7D%0A    fmt.Println()\n %0A%7D%0A\n",
            "lines": "33"
        },
        {
            "label": "2026-04-07_10-44-46",
            "content": "@@ -33,17 +33,16 @@\n ain() %7B%0A\n-%0A\n     var \n@@ -46,186 +46,34 @@\n ar t\n-ament, tambus int%0A    fmt.Scan(&tament)%0A    %0A    entradas := make(%5B%5Dstring, tament)%0A%0A    for i := 0; i %3C tament; i++ %7B%0A        fmt.Scan(&entradas%5Bi%5D)%0A    %7D%0A%0A    fmt.Scan(&tambus)\n+otalAlbum, totalPossui int\n %0A%0A  \n@@ -77,22 +77,21 @@\n %0A    con\n-sultas\n+tagem\n  := make\n@@ -95,497 +95,79 @@\n ake(\n-%5B%5Dstring, tambus)%0A    for i := 0; i %3C tambus; i++ %7B%0A        fmt.Scan(&consultas%5Bi%5D)%0A    %7D%0A    %0A    ocorrencias := make(%5B%5Dint, tambus)%0A%0A    for i := 0; i %3C tambus; i++ %7B%0A        for j := 0; j %3C tament; j++ %7B%0A            if consultas%5Bi%5D == entradas%5Bj%5D %7B%0A                ocorrencias%5Bi%5D++%0A            %7D%0A        %7D%0A    %7D%0A    %0A    for i := 0; i %3C tambus; i++ %7B%0A        fmt.Printf(%22%25d%22, ocorrencias%5Bi%5D)%0A        if(i %3C tambus-1) %7B%0A            fmt.Print(%22 %22)%0A        %7D%0A    %7D%0A    fmt.Println()%0A%0A    %0A%0A\n+map%5Bint%5Dint)%0A%0A    for i := 0; i %3C totalPossui; i++ %7B%0A        var num int\n %0A%7D%0A\n",
            "lines": "10"
        },
        {
            "label": "2026-04-07_10-44-46",
            "content": "@@ -37,16 +37,17 @@\n ) %7B%0A\n+%0A\n     var \n n in\n@@ -42,17 +42,30 @@\n     var \n-n\n+tament, tambus\n  int%0A   \n@@ -79,24 +79,32 @@\n an(&\n-n)%0A    descasado\n+tament)%0A    %0A    entrada\n s :=\n@@ -115,16 +115,25 @@\n e(%5B%5D\n+str\n in\n-t, n\n+g, tament\n )%0A\n+%0A\n     \n@@ -140,38 +140,44 @@\n for i := 0; i %3C \n-n\n+tament\n ; i++\n+ \n %7B%0A        fmt.Sc\n@@ -184,39 +184,207 @@\n an(&\n-descasados%5Bi%5D)%0A    %7D%0A    k := 0\n+entradas%5Bi%5D)%0A    %7D%0A%0A    fmt.Scan(&tambus)%0A%0A    consultas := make(%5B%5Dstring, tambus)%0A    for i := 0; i %3C tambus; i++ %7B%0A        fmt.Scan(&consultas%5Bi%5D)%0A    %7D%0A    %0A    ocorrencias := make(%5B%5Dint, tambus)%0A\n %0A   \n@@ -404,14 +404,20 @@\n i %3C \n-n\n+tambus\n ; i++\n+ \n %7B%0A  \n@@ -435,25 +435,27 @@\n  := \n-i + 1\n+0\n ; j %3C \n-n\n+tament\n ; j++\n+ \n %7B%0A  \n@@ -471,88 +471,70 @@\n  if \n-descasados%5Bi%5D == (-1)*descasado\n+consultas%5Bi%5D == entrada\n s%5Bj%5D \n-&& descasados%5Bi%5D != 0 && descasados%5Bj%5D != 0%7B\n+%7B%0A                ocorrencias%5Bi%5D++\n %0A   \n@@ -546,132 +546,176 @@\n     \n+%7D%0A\n     \n-k++%0A\n     \n+%7D%0A\n     \n+%7D%0A\n     \n+%0A\n     \n-descasados%5Bi%5D = 0%0A                descasados%5Bj%5D = 0%0A                break%0A        \n+for i := 0; i %3C tambus; i++ %7B%0A        fmt.Printf(%22%25d%22, ocorrencias%5Bi%5D)%0A        if(i %3C tambus-1) %7B%0A            fmt.Print(%22 %22)%0A\n     \n-%7D%0A\n     \n+%7D%0A\n     %7D%0A\n-%7D%0A\n     \n@@ -730,8 +730,16 @@\n tln(\n-k\n )%0A\n-%7D\n+%0A    %0A%0A%0A%7D%0A\n",
            "lines": "42"
        },
        {
            "label": "2026-04-07_10-44-46",
            "content": "@@ -6,17 +6,16 @@\n ge main%0A\n-%0A\n import %22\n@@ -19,17 +19,16 @@\n t %22fmt%22%0A\n-%0A\n func mai\n@@ -37,23 +37,26 @@\n ) %7B%0A\n-%09\n+    \n var n\n-, e\n  int%0A\n-%09\n+    \n fmt.\n@@ -66,48 +66,47 @@\n n(&n\n-, &e)%0A%09//var j int%0A%0A%09vivos := %5B%5Dint%7B%7D%0A%0A%09\n+)%0A    descasados := make(%5B%5Dint, n)%0A    \n for \n@@ -127,76 +127,64 @@\n  i++\n- \n %7B%0A\n-%0A%09%09vivos = append(vivos, i+1)%0A%09%7D%0A%0A%09fmt.Print(%22%5B%22)%0A    var j int%0A%09\n+        fmt.Scan(&descasados%5Bi%5D)%0A    %7D%0A    k := 0%0A    \n for \n@@ -201,19 +201,17 @@\n %3C n; i++\n- %7B%0A\n+%7B\n %0A       \n@@ -215,79 +215,130 @@\n     \n-if(vivos%5Bi%5D == e)%7B%0A            vivos%5Bi + 1%5D = 0%0A            if(e %3E= n) \n+for j := i + 1; j %3C n; j++%7B%0A            if descasados%5Bi%5D == (-1)*descasados%5Bj%5D && descasados%5Bi%5D != 0 && descasados%5Bj%5D != 0\n %7B%0A  \n@@ -355,12 +355,11 @@\n     \n-e==1\n+k++\n %0A   \n@@ -371,38 +371,63 @@\n     \n-%7D else %7B%0A                e +=2\n+    descasados%5Bi%5D = 0%0A                descasados%5Bj%5D = 0\n %0A   \n@@ -439,24 +439,22 @@\n     \n-%7D%0A%0A\n     \n-    \n+break%0A\n     \n-%0A\n     \n@@ -459,25 +459,24 @@\n       %7D%0A\n-%0A\n         \n if(vivos\n@@ -471,72 +471,28 @@\n     \n-if(vivos%5Bi%5D != 0)%7B%0A%09%09fmt.Print(vivos%5Bi%5D, %22 %22)%0A%09%7D%0A%09fmt.Print(%22%5D%22)%0A%0A%7D%0A\n+%7D%0A%7D%0A    fmt.Println(k)%0A%7D\n",
            "lines": "22"
        },
        {
            "label": "2026-04-07_10-44-46",
            "content": "@@ -6,16 +6,17 @@\n ge main%0A\n+%0A\n import %22\n@@ -30,59 +30,157 @@\n unc \n-primo(num int) int %7B%0A%0A%0A%0A    return%0A%7D%0A%0Afunc main() %7B\n+main() %7B%0A%09var n, e int%0A%09fmt.Scan(&n, &e)%0A%09//var j int%0A%0A%09vivos := %5B%5Dint%7B%7D%0A%0A%09for i := 0; i %3C n; i++ %7B%0A%0A%09%09vivos = append(vivos, i+1)%0A%09%7D%0A%0A%09fmt.Print(%22%5B%22)\n %0A   \n@@ -188,69 +188,297 @@\n var \n-num\n+j\n  int%0A\n-    fmt.Scan(num)%0A    val %0A    fmt.Println(primo(num))\n+%09for i := 0; i %3C n; i++ %7B%0A%0A        if(vivos%5Bi%5D == e)%7B%0A            vivos%5Bi + 1%5D = 0%0A            if(e %3E= n) %7B%0A                e==1%0A            %7D else %7B%0A                e +=2%0A            %7D%0A%0A            %0A        %7D%0A%0A        if(vivos%5Bi%5D != 0)%7B%0A%09%09fmt.Print(vivos%5Bi%5D, %22 %22)%0A%09%7D%0A%09fmt.Print(%22%5D%22)%0A\n %0A%7D%0A\n",
            "lines": "37"
        },
        {
            "label": "2026-04-07_10-44-46",
            "content": "@@ -23,384 +23,135 @@\n mt%22%0A\n+%0A\n func \n-main() %7B%0A    var h, p, f, d int%0A    fmt.Scan(&h, &p, &f, &d)%0A    %0A    for %7B%0A        f += d%0A         if(f %3E 15)%7B%0A            f = 0%0A        %7D else if(f %3C 0)%7B%0A            f = 15%0A        %7D %0A        if(f == h)%7B%0A            fmt.Println(%22S%22)%0A            break%0A        %7D else if(f == p)%7B%0A            fmt.Println(%22N%22)%0A            break%0A        %7D%0A       %0A            %0A        %0A    %7D\n+primo(num int) int %7B%0A%0A%0A%0A    return%0A%7D%0A%0Afunc main() %7B%0A    var num int%0A    fmt.Scan(num)%0A    val %0A    fmt.Println(primo(num))\n %0A%7D%0A\n",
            "lines": "16"
        },
        {
            "label": "2026-04-07_10-44-46",
            "content": "@@ -41,28 +41,366 @@\n     \n-fmt.Println(%22qxcode%22)\n+var h, p, f, d int%0A    fmt.Scan(&h, &p, &f, &d)%0A    %0A    for %7B%0A        f += d%0A         if(f %3E 15)%7B%0A            f = 0%0A        %7D else if(f %3C 0)%7B%0A            f = 15%0A        %7D %0A        if(f == h)%7B%0A            fmt.Println(%22S%22)%0A            break%0A        %7D else if(f == p)%7B%0A            fmt.Println(%22N%22)%0A            break%0A        %7D%0A       %0A            %0A        %0A    %7D\n %0A%7D%0A\n",
            "lines": "25"
        },
        {
            "label": "2026-04-07_10-44-46",
            "content": "@@ -41,1574 +41,28 @@\n     \n-var n, e int%0A    fmt.Scan(&n, &e)%0A%0A%0A    pessoas := make(%5B%5Dint, n)%0A%0A    for i:= 0; i%3Cn;i++ %7B%0A        pessoas%5Bi%5D = i+1%0A    %7D%0A%0A    var achou bool%0A    var valor int%0A    for i := 0; i %3C n; i++ %7B%0A        achou = false%0A        fmt.Print(%22%5B %22)%0A        for j := 0; j %3C n; j++ %7B%0A            if pessoas%5Bj%5D != 0 %7B%0A                fmt.Print(pessoas%5Bj%5D)%0A            %7D%0A            if pessoas%5Bj%5D == e %7B%0A                fmt.Print(%22%3E %22)%0A            %7D else %7B%0A                fmt.Print(%22 %22)%0A            %7D%0A        %7D%0A        fmt.Println(%22%5D%22)%0A        for j := 0; j %3C n; j++ %7B%0A            if pessoas%5Bj%5D == e %7B%0A                for k := j + 1; k %3C n; k++ %7B%0A                    if pessoas%5Bk%5D != 0 %7B%0A                        pessoas%5Bk%5D = 0%0A                        achou = true%0A                        valor = k + 1%0A                        break %0A                    %7D%0A                %7D%0A                if !achou %7B%0A                    for k := 0; k %3C j; k++ %7B%0A                        if pessoas%5Bk%5D != 0 %7B%0A                            pessoas%5Bk%5D = 0%0A                            achou = true%0A                            valor = k + 1%0A                            break %0A                        %7D%0A                    %7D%0A                %7D%0A                if(e == n - 1) %7B%0A                    for k := 0; k %3C n; k++ %7B%0A                        if pessoas%5Bk%5D != 0 %7B%0A                            e = k%0A                            break%0A                        %7D%0A                    %7D%0A                %7D else %7B%0A                    e = valor%0A                %7D%0A                break%0A            %7D%0A        %7D%0A    %7D%0A%0A\n+fmt.Println(%22qxcode%22)\n %0A%7D%0A\n",
            "lines": "5"
        },
        {
            "label": "2026-04-07_10-44-46",
            "content": "@@ -46,18 +46,145 @@\n ar n\n-ome string\n+, e int%0A    fmt.Scan(&n, &e)%0A%0A%0A    pessoas := make(%5B%5Dint, n)%0A%0A    for i:= 0; i%3Cn;i++ %7B%0A        pessoas%5Bi%5D = i+1%0A    %7D%0A%0A    var achou bool\n %0A   \n@@ -188,19 +188,21 @@\n     var \n-idd\n+valor\n  int%0A   \n@@ -207,106 +207,227 @@\n    f\n-mt.Scanf(%22%25s%22, &nome)%0A\n+or i := 0; i %3C n; i++ %7B%0A        achou = false%0A  \n     \n+  \n fmt.\n-Scanf(%22%25d%22, &idd)%0A%0A    fmt.Printf(%22%25s eh %22, nome)%0A%0A%0A    if(idd %3C 12)\n+Print(%22%5B %22)%0A        for j := 0; j %3C n; j++ %7B%0A            if pessoas%5Bj%5D != 0 %7B%0A                fmt.Print(pessoas%5Bj%5D)%0A            %7D%0A            if pessoas%5Bj%5D == e \n %7B%0A  \n@@ -424,32 +424,40 @@\n  == e %7B%0A        \n+ \n+       \n fmt.Printf(%22cria\n@@ -453,61 +453,44 @@\n rint\n-f\n (%22\n-crianca%5Cn%22)%0A    %7D else if(idd %3E= 12 && idd %3C 18)%7B%0A\n+%3E %22)%0A            %7D else %7B%0A        \n     \n@@ -506,160 +506,996 @@\n rint\n-f\n (%22\n-jovem%5Cn%22)%0A    %7D else if(idd %3E= 18 && idd %3C 65)%7B%0A        fmt.Printf(%22adulto%5Cn%22)%0A    %7D else if(idd %3E= 65 && idd %3C 1000)%7B%0A        fmt.Printf(%22idoso%5Cn%22)%0A\n+ %22)%0A            %7D%0A        %7D%0A        fmt.Println(%22%5D%22)%0A        for j := 0; j %3C n; j++ %7B%0A            if pessoas%5Bj%5D == e %7B%0A                for k := j + 1; k %3C n; k++ %7B%0A                    if pessoas%5Bk%5D != 0 %7B%0A                        pessoas%5Bk%5D = 0%0A                        achou = true%0A                        valor = k + 1%0A                        break %0A                    %7D%0A                %7D%0A                if !achou %7B%0A                    for k := 0; k %3C j; k++ %7B%0A                        if pessoas%5Bk%5D != 0 %7B%0A                            pessoas%5Bk%5D = 0%0A                            achou = true%0A                            valor = k + 1%0A                            break %0A                        %7D%0A                    %7D%0A                %7D%0A                if(e == n - 1) %7B%0A                    for k := 0; k %3C n; k++ %7B%0A                        if pessoas%5Bk%5D != 0 %7B%0A                            e = k%0A                            break%0A                        %7D%0A                    %7D%0A            \n     \n@@ -1500,16 +1500,17 @@\n   %7D else\n+ \n %7B%0A      \n@@ -1515,36 +1515,100 @@\n     \n+    \n-fmt.Printf(%22mumia%5Cn%22)%0A    %7D%0A\n+        e = valor%0A                %7D%0A                break%0A            %7D%0A        %7D%0A    \n %7D%0A%0A%0A\n+%7D%0A\n",
            "lines": "66"
        },
        {
            "label": "2026-04-07_10-44-46",
            "content": "@@ -17,42 +17,13 @@\n ort \n-(%0A    %22fmt%22%0A    %22math%22%0A    ) %0A    \n+%22fmt%22\n %0Afun\n@@ -45,46 +45,35 @@\n var \n-a, b, n, venc, atual int\n+nome string\n %0A    v\n-enc = -1\n+ar idd int\n %0A   \n@@ -85,124 +85,169 @@\n Scan\n-(&n)%0A    melhorDiferenca := 101%0A    for i := 0; i %3C n; i++ %7B%0A        fmt.Scan(&a, &b)%0A%0A        if a\n+f(%22%25s%22, &nome)%0A    fmt.Scanf(%22%25d%22, &idd)%0A%0A    fmt.Printf(%22%25s eh %22, nome)%0A%0A%0A    if(idd %3C 12)%7B%0A        fmt.Printf(%22crianca%5Cn%22)%0A    %7D else if(idd\n  %3E= 1\n-0\n+2\n  && \n-b %3E= 10\n+idd %3C 18)\n %7B%0A  \n@@ -256,234 +256,137 @@\n     \n-    atual = int(math.Abs(float64(a - b)))%0A%0A            if atual %3C melhorDiferenca %7B%0A                melhorDiferenca = atual%0A                venc = i %0A            %7D%0A             %0A            %7D%0A        %0A    %7D%0A%0A    if venc == -1 \n+fmt.Printf(%22jovem%5Cn%22)%0A    %7D else if(idd %3E= 18 && idd %3C 65)%7B%0A        fmt.Printf(%22adulto%5Cn%22)%0A    %7D else if(idd %3E= 65 && idd %3C 1000)\n %7B%0A  \n@@ -404,24 +404,18 @@\n rint\n-ln(%22sem ganhador\n+f(%22idoso%5Cn\n %22)%0A \n@@ -423,17 +423,16 @@\n   %7D else\n- \n %7B%0A      \n@@ -446,23 +446,27 @@\n rint\n-ln(venc\n+f(%22mumia%5Cn%22\n )%0A    %7D%0A\n %0A%0A%7D%0A\n@@ -465,11 +465,8 @@\n   %7D%0A\n-%0A%0A%7D%0A\n+%7D\n %0A%0A%0A\n",
            "lines": "25"
        },
        {
            "label": "2026-04-07_10-44-46",
            "content": "@@ -36,18 +36,27 @@\n  %22math%22%0A\n-)%0A\n+    ) %0A    \n %0Afunc ma\n@@ -80,221 +80,491 @@\n  b, \n-c, p, v1, fin float64%0A    fmt.Scanf(%22%25f%22, &a)%0A    fmt.Scanf(%22%25f%22, &b)%0A    fmt.Scanf(%22%25f%22, &c)%0A    p = (a + b + c ) / 2%0A    v1 = p * (p - a) * (p - b) * (p - c)%0A    fin\n+n, venc, atual int%0A    venc = -1%0A    fmt.Scan(&n)%0A    melhorDiferenca := 101%0A    for i := 0; i %3C n; i++ %7B%0A        fmt.Scan(&a, &b)%0A%0A        if a %3E= 10 && b %3E= 10%7B%0A            atual = int(math.Abs(float64(a - b)))%0A%0A            if atual %3C melhorDiferenca %7B%0A                melhorDiferenca\n  = \n-m\n at\n-h.Sqrt(v1)%0A    fmt.Printf(%22%25.2f%5Cn%22, fin)%0A%0A%7D\n+ual%0A                venc = i %0A            %7D%0A             %0A            %7D%0A        %0A    %7D%0A%0A    if venc == -1 %7B%0A        fmt.Println(%22sem ganhador%22)%0A    %7D else %7B%0A        fmt.Println(venc)%0A    %7D%0A%0A%0A%7D%0A%0A%0A\n %0A\n",
            "lines": "37"
        },
        {
            "label": "2026-04-07_10-44-46",
            "content": "@@ -17,1685 +17,275 @@\n ort \n-%22fmt%22%0Afunc main() %7B%0A    var n, e int%0A    fmt.Scan(&n, &e)%0A%0A%0A    pessoas := make(%5B%5Dint, n)%0A%0A    for i:= 0; i%3Cn;i++ %7B%0A        pessoas%5Bi%5D = i+1%0A    %7D%0A%0A    var achou bool%0A    var valor int%0A    for i := 0; i %3C n - 1; i++ %7B%0A        achou = false%0A        fmt.Print(%22%5B %22)%0A        for j := 0; j %3C n; j++ %7B%0A            if pessoas%5Bj%5D == 0%7B%0A                continue%0A            %7D%0A            if pessoas%5Bj%5D != 0 %7B%0A                fmt.Print(pessoas%5Bj%5D)%0A            %7D%0A            if pessoas%5Bj%5D == e %7B%0A                fmt.Print(%22%3E %22)%0A            %7D else %7B%0A                fmt.Print(%22 %22)%0A            %7D%0A        %7D%0A        %0A        fmt.Println(%22%5D%22)%0A        for j := 1; j %3C= n; j++ %7B%0A            if pessoas%5Bj%5D == e %7B%0A                for k := j + 1; k %3C n; k++ %7B%0A                    if pessoas%5Bk%5D != 0 %7B%0A                        pessoas%5Bk%5D = 0%0A                        achou = true%0A                        valor = k + 1%0A                        break %0A                    %7D%0A                %7D%0A                if !achou %7B%0A                    for k := 1; k %3C= j; k++ %7B%0A                        if pessoas%5Bk%5D != 0 %7B%0A                            pessoas%5Bk%5D = 0%0A                            achou = true%0A                            valor = k + 1%0A                            break %0A                        %7D%0A                    %7D%0A                %7D%0A                if(e == n - 1) %7B%0A                    for k := 1; k %3C= n; k++ %7B%0A                        if pessoas%5Bk%5D != 0 %7B%0A                            e = k%0A                            break%0A                        %7D%0A                    %7D%0A                %7D else %7B%0A                    e = valor%0A                %7D%0A                break%0A            %7D%0A        %7D%0A    %7D%0A\n+(%0A    %22fmt%22%0A    %22math%22%0A)%0A%0Afunc main() %7B%0A    var a, b, c, p, v1, fin float64%0A    fmt.Scanf(%22%25f%22, &a)%0A    fmt.Scanf(%22%25f%22, &b)%0A    fmt.Scanf(%22%25f%22, &c)%0A    p = (a + b + c ) / 2%0A    v1 = p * (p - a) * (p - b) * (p - c)%0A    fin = math.Sqrt(v1)%0A    fmt.Printf(%22%25.2f%5Cn%22, fin)\n %0A%0A%7D%0A\n",
            "lines": "17"
        },
        {
            "label": "2026-04-07_10-44-46",
            "content": "@@ -23,54 +23,241 @@\n mt%22%0A\n-%0A\n func \n-div(num, rest int)  %7B%0A%0A    if num == 0 %7B\n+main() %7B%0A    var n, e int%0A    fmt.Scan(&n, &e)%0A%0A%0A    pessoas := make(%5B%5Dint, n)%0A%0A    for i:= 0; i%3Cn;i++ %7B%0A        pessoas%5Bi%5D = i+1%0A    %7D%0A%0A    var achou bool%0A    var valor int%0A    for i := 0; i %3C n - 1; i++ %7B%0A        achou = false\n %0A   \n@@ -274,38 +274,162 @@\n rint\n-f\n (%22\n-%25d %25d%22, num, rest)%0A\n+%5B %22)%0A        for j := 0; j %3C n; j++ %7B%0A            if pessoas%5Bj%5D == 0%7B%0A                continue%0A            %7D%0A            if pessoas%5Bj%5D != 0 %7B%0A  \n         \n fmt.\n@@ -416,32 +416,38 @@\n = 0 %7B%0A          \n+      \n fmt.Println()%0A  \n@@ -439,19 +439,27 @@\n mt.Print\n-ln(\n+(pessoas%5Bj%5D\n )%0A      \n@@ -464,15 +464,8 @@\n     \n-return%0A\n     \n@@ -474,152 +474,1228 @@\n     \n-div(num/2, num %25 2)%0A    %0A    fmt.Print(num, %22 %22, rest)%0A    fmt.Println()%0A%0A%7D%0A%0Afunc main() %7B%0A    var n int%0A    fmt.Scan(&n)%0A    %0A    div(n/2, n%252)\n+        if pessoas%5Bj%5D == e %7B%0A                fmt.Print(%22%3E %22)%0A            %7D else %7B%0A                fmt.Print(%22 %22)%0A            %7D%0A        %7D%0A        %0A        fmt.Println(%22%5D%22)%0A        for j := 1; j %3C= n; j++ %7B%0A            if pessoas%5Bj%5D == e %7B%0A                for k := j + 1; k %3C n; k++ %7B%0A                    if pessoas%5Bk%5D != 0 %7B%0A                        pessoas%5Bk%5D = 0%0A                        achou = true%0A                        valor = k + 1%0A                        break %0A                    %7D%0A                %7D%0A                if !achou %7B%0A                    for k := 1; k %3C= j; k++ %7B%0A                        if pessoas%5Bk%5D != 0 %7B%0A                            pessoas%5Bk%5D = 0%0A                            achou = true%0A                            valor = k + 1%0A                            break %0A                        %7D%0A                    %7D%0A                %7D%0A                if(e == n - 1) %7B%0A                    for k := 1; k %3C= n; k++ %7B%0A                        if pessoas%5Bk%5D != 0 %7B%0A                            e = k%0A                            break%0A                        %7D%0A                    %7D%0A                %7D else %7B%0A                    e = valor%0A                %7D%0A                break%0A            %7D%0A        %7D%0A    %7D%0A\n %0A%0A%7D%0A\n",
            "lines": "70"
        },
        {
            "label": "2026-04-07_10-44-46",
            "content": "@@ -23,336 +23,165 @@\n mt%22%0A\n+%0A\n func \n-main() %7B%0A    var ta\n+div(nu\n m, r\n-o\n+es\n t int\n-%0A    fmt.Scan(&tam)%0A    fmt.Scan(&rot)%0A    t := make(%5B%5Dint, tam)%0A    for i := 0; i %3C tam; i++ %7B%0A        fmt.Scan(&t%5Bi%5D)%0A    %7D%0A    var ult int%0A    for i:= 0; i %3C rot; i++ %7B%0A        ult = t%5Btam-1%5D%0A        for j := tam - 1; j %3E 0; j-- %7B%0A            t%5Bj%5D = t%5Bj-1%5D%0A   \n+)  %7B%0A%0A    if num == 0 %7B%0A        fmt.Printf(%22%25d %25d%22, num, rest)%0A        fmt.Println()%0A        return%0A\n     \n- \n %7D%0A    \n-    t%5B0%5D = ult\n+div(num/2, num %25 2)\n %0A    \n-%7D\n %0A   \n@@ -195,52 +195,28 @@\n int(\n-%22%5B %22)%0A    for i:= 0; i %3C tam; i++ %7B%0A \n+num, %22 %22, rest)%0A\n     \n-   \n fmt.\n@@ -224,119 +224,84 @@\n rint\n-(t%5Bi%5D)%0A        if(i %3C tam - 1)%7B%0A       \n+ln()%0A%0A%7D%0A%0Afunc main() %7B%0A    var n int%0A\n     \n- \n fmt.\n-Print(%22 %22)%0A        %7D%0A    %7D%0A    fmt.Print(%22 %5D%22)%0A    fmt.Println()\n+Scan(&n)%0A    %0A    div(n/2, n%252)%0A\n %0A%7D%0A\n",
            "lines": "24"
        },
        {
            "label": "2026-04-07_10-44-46",
            "content": "@@ -6,17 +6,16 @@\n ge main%0A\n-%0A\n import %22\n@@ -19,17 +19,16 @@\n t %22fmt%22%0A\n-%0A\n func mai\n@@ -37,31 +37,41 @@\n ) %7B%0A\n-%09var a, b\n+    var tam, rot\n  int%0A\n-%09\n+    \n fmt.Scan\n f(%22%25\n@@ -70,69 +70,468 @@\n Scan\n-f(%22%25d %25d%22, &a, &b)%0A%09fmt.Println(a + b)%0A%0A%09fmt.Println(%22qxcode%22\n+(&tam)%0A    fmt.Scan(&rot)%0A    t := make(%5B%5Dint, tam)%0A    for i := 0; i %3C tam; i++ %7B%0A        fmt.Scan(&t%5Bi%5D)%0A    %7D%0A    var ult int%0A    for i:= 0; i %3C rot; i++ %7B%0A        ult = t%5Btam-1%5D%0A        for j := tam - 1; j %3E 0; j-- %7B%0A            t%5Bj%5D = t%5Bj-1%5D%0A        %7D%0A        t%5B0%5D = ult%0A    %7D%0A    fmt.Print(%22%5B %22)%0A    for i:= 0; i %3C tam; i++ %7B%0A        fmt.Print(t%5Bi%5D)%0A        if(i %3C tam - 1)%7B%0A            fmt.Print(%22 %22)%0A        %7D%0A    %7D%0A    fmt.Print(%22 %5D%22)%0A    fmt.Println(\n )%0A%7D%0A\n",
            "lines": "28"
        },
        {
            "label": "2026-04-07_10-44-46",
            "content": "package main\n\nimport \"fmt\"\n\nfunc main() {\n\tvar a, b int\n\tfmt.Scanf(\"%d %d\", &a, &b)\n\tfmt.Println(a + b)\n\n\tfmt.Println(\"qxcode\")\n}\n",
            "lines": "11"
        }
    ]
}